{
        "bundle_plugin_1": {
            "bundle_info": {
                "bundle_name": "Starter Bundle",
                "bundle_author": "Test",
                "bundle_author_link": "http://raison.co",                
                "bundle_description": "This is a test bundle"
            },
            
        "bundle_plugins": {
            
	            "plugin_1": {
	                "plugin_slug": "jetpack",
	                "plugin_path": "http://downloads.wordpress.org/plugin/jetpack.1.3.zip",
	                "plugin_install": "jetpack/jetpack.php"
	            },
	            "plugin_2": {
	                "plugin_slug": "debug-bar-actions-and-filters-addon",
	                "plugin_path": "http://downloads.wordpress.org/plugin/debug-bar-actions-and-filters-addon.1.4.1.zip",
	                "plugin_install": "debug-bar-actions-and-filters-addon/debug-bar-action-and-filters-addon.php"
	            },
	            "plugin_3": {
	                "plugin_slug": "tumblr-importer",
	                "plugin_path": "http://downloads.wordpress.org/plugin/tumblr-importer.0.5.zip",
	                "plugin_install": "tumblr-importer/tumblr-importer.php"
	            }
            
            }
            
            
        },
        "bundle_plugin_2": {
            "bundle_info": {
                "bundle_name": "Debug Bundle",
                "bundle_author": "Raison",
                "bundle_author_link": "http://raison.co",
                "bundle_description": "This is the debug bundle"
            },
            
			"bundle_plugins": {

            "plugin_1": {
                "plugin_slug": "debug-bar",
                "plugin_path": "http://downloads.wordpress.org/plugin/debug-bar.0.8.1.zip",
                "plugin_install": "debug-bar/debug-bar.php"
            },
            "plugin_2": {
                "plugin_slug": "debug-bar-constants",
                "plugin_path": "http://downloads.wordpress.org/plugin/debug-bar-constants.1.3.zip",
                "plugin_install": "debug-bar-constants/debug-bar-constants.php"
            },
            "plugin_3": {
                "plugin_slug": "debug-bar-post-types",
                "plugin_path": "http://downloads.wordpress.org/plugin/debug-bar-post-types.1.1.zip",
                "plugin_install": "debug-bar-post-types/debug-bar-post-types.php"
            }
            
            }
        }
    }
